dragonion_core/__init__.py
dragonion_core/proto/__init__.py
dragonion_core/proto/encryption/__init__.py
dragonion_core/proto/encryption/identity.py
dragonion_core/proto/file/__init__.py
dragonion_core/proto/file/auth.py
dragonion_core/proto/web/__init__.py
dragonion_core/proto/web/webmessage/__init__.py
dragonion_core/proto/web/webmessage/connection.py
dragonion_core/proto/web/webmessage/message.py
dragonion_core/proto/web/webmessage/server.py
dragonion_core/proto/web/webmessage/webmessage.py
dragonion_core-0.1.1.dist-info/METADATA
dragonion_core-0.1.1.dist-info/WHEEL
dragonion_core-0.1.1.dist-info/RECORD
